odoo/addons/website_sale_product_attribute_value_filter_existing/README.rst
odoo/addons/website_sale_product_attribute_value_filter_existing/__init__.py
odoo/addons/website_sale_product_attribute_value_filter_existing/__manifest__.py
odoo/addons/website_sale_product_attribute_value_filter_existing/controllers/__init__.py
odoo/addons/website_sale_product_attribute_value_filter_existing/controllers/main.py
odoo/addons/website_sale_product_attribute_value_filter_existing/data/demo.xml
odoo/addons/website_sale_product_attribute_value_filter_existing/i18n/es.po
odoo/addons/website_sale_product_attribute_value_filter_existing/i18n/website_sale_product_attribute_value_filter_existing.pot
odoo/addons/website_sale_product_attribute_value_filter_existing/readme/CONTRIBUTORS.rst
odoo/addons/website_sale_product_attribute_value_filter_existing/readme/DESCRIPTION.rst
odoo/addons/website_sale_product_attribute_value_filter_existing/readme/USAGE.rst
odoo/addons/website_sale_product_attribute_value_filter_existing/static/description/icon.png
odoo/addons/website_sale_product_attribute_value_filter_existing/static/description/index.html
odoo/addons/website_sale_product_attribute_value_filter_existing/static/src/js/website_sale_product_attribute_value_filter_existing_tour.js
odoo/addons/website_sale_product_attribute_value_filter_existing/tests/__init__.py
odoo/addons/website_sale_product_attribute_value_filter_existing/tests/test_website_sale_product_attribute_value_filter_existing.py
odoo/addons/website_sale_product_attribute_value_filter_existing/views/assets.xml
odoo/addons/website_sale_product_attribute_value_filter_existing/views/templates.xml
odoo12_addon_website_sale_product_attribute_value_filter_existing-12.0.1.0.0.dist-info/METADATA
odoo12_addon_website_sale_product_attribute_value_filter_existing-12.0.1.0.0.dist-info/WHEEL
odoo12_addon_website_sale_product_attribute_value_filter_existing-12.0.1.0.0.dist-info/top_level.txt
odoo12_addon_website_sale_product_attribute_value_filter_existing-12.0.1.0.0.dist-info/RECORD
